MANIFEST.in
setup.py
cmsplugin_facebook/__init__.py
cmsplugin_facebook/cms_plugins.py
cmsplugin_facebook/models.py
cmsplugin_facebook.egg-info/PKG-INFO
cmsplugin_facebook.egg-info/SOURCES.txt
cmsplugin_facebook.egg-info/dependency_links.txt
cmsplugin_facebook.egg-info/not-zip-safe
cmsplugin_facebook.egg-info/top_level.txt
cmsplugin_facebook/migrations/0001_initial.py
cmsplugin_facebook/migrations/0002_auto__add_field_facebooklikebox_transparent.py
cmsplugin_facebook/migrations/__init__.py
cmsplugin_facebook/templates/cmsplugin_facebook/likebox.html
cmsplugin_facebook/templates/cmsplugin_facebook/likebutton.html
cmsplugin_facebook/templates/cmsplugin_facebook/sharebutton.html