Metadata-Version: 1.0
Name: cmsplugin-facebook
Version: 0.2.0
Summary: Django CMS Facebook Plugins
Home-page: http://github.com/chrisglass/cmsplugin_facebook
Author: Christopher Glass
Author-email: christopher.glass@divio.ch
License: BSD
Platform: UNKNOWN
Classifier: Development Status :: 4 - Beta
Classifier: Framework :: Django
Classifier: Intended Audience :: Developers
Classifier: License :: OSI Approved :: BSD License
Classifier: Operating System :: OS Independent
Classifier: Programming Language :: Python
Classifier: Topic :: Internet :: WWW/HTTP
